odoo8_addon_account_voucher_invoice_number-8.0.1.0.0-py2.7-nspkg.pth
odoo8_addon_account_voucher_invoice_number-8.0.1.0.0.dist-info/DESCRIPTION.rst
odoo8_addon_account_voucher_invoice_number-8.0.1.0.0.dist-info/METADATA
odoo8_addon_account_voucher_invoice_number-8.0.1.0.0.dist-info/RECORD
odoo8_addon_account_voucher_invoice_number-8.0.1.0.0.dist-info/WHEEL
odoo8_addon_account_voucher_invoice_number-8.0.1.0.0.dist-info/metadata.json
odoo8_addon_account_voucher_invoice_number-8.0.1.0.0.dist-info/namespace_packages.txt
odoo8_addon_account_voucher_invoice_number-8.0.1.0.0.dist-info/top_level.txt
odoo_addons/account_voucher_invoice_number/README.rst
odoo_addons/account_voucher_invoice_number/__init__.py
odoo_addons/account_voucher_invoice_number/__openerp__.py
odoo_addons/account_voucher_invoice_number/images/vouchers.png
odoo_addons/account_voucher_invoice_number/models/__init__.py
odoo_addons/account_voucher_invoice_number/models/account_voucher.py
odoo_addons/account_voucher_invoice_number/tests/__init__.py
odoo_addons/account_voucher_invoice_number/tests/test_account_voucher.py
odoo_addons/account_voucher_invoice_number/views/account_voucher_view.xml
